buildver/__init__.py
buildver/__main__.py
buildver/cli/__init__.py
buildver/error/__init__.py
tests/__init__.py
buildver-0.0.4.dist-info/LICENSE
buildver-0.0.4.dist-info/METADATA
buildver-0.0.4.dist-info/WHEEL
buildver-0.0.4.dist-info/entry_points.txt
buildver-0.0.4.dist-info/top_level.txt
buildver-0.0.4.dist-info/RECORD
