Metadata-Version: 2.1
Name: buildver
Version: 0.0.4
Summary: Tool to build Python packages with built-in intuitive versioning mechanism
Home-page: https://github.com/pyrustic/buildver
Author: Pyrustic Evangelist
Author-email: rusticalex@yahoo.com
Maintainer: Pyrustic Evangelist
Maintainer-email: rusticalex@yahoo.com
License: MIT
Keywords: CLI,tool,versioning,wheel,build,packaging,distribution
Platform: UNKNOWN
Classifier: Programming Language :: Python :: 3
Classifier: License :: OSI Approved :: MIT License
Classifier: Operating System :: OS Independent
Requires-Python: >=3.5
License-File: LICENSE
Requires-Dist: subrun
